README.md
setup.py
zelas2/Ellipse.py
zelas2/JCFI_More.py
zelas2/Multispectral.py
zelas2/RedundancyElimination.py
zelas2/TheHeartOfTheMilitaryGod.py
zelas2/__init__.py
zelas2/dxf_dwg.py
zelas2/graphCut.py
zelas2/mmdet3d_base.py
zelas2/ransac.py
zelas2/shield.py
zelas2/shield_plus.py
zelas2/supervoxel.py
zelas2/voxel.py
zelas2.egg-info/PKG-INFO
zelas2.egg-info/SOURCES.txt
zelas2.egg-info/dependency_links.txt
zelas2.egg-info/top_level.txt