Metadata-Version: 2.1
Name: zelas2
Version: 1.3.0.251228
Summary: a ligh weight menu , support both win and mac 
Home-page: UNKNOWN
Author: Ze You, Shichao Wang, Huaxin Chen, Yimo Geng, Yuqing Wang, Jun Wang
Author-email: youze1997@163.com
License: UNKNOWN
Keywords: python,menu,dumb_menu,windows,mac,linux
Platform: UNKNOWN
Classifier: Development Status :: 1 - Planning
Classifier: Intended Audience :: Developers
Classifier: Programming Language :: Python :: 3
Classifier: Operating System :: Unix
Classifier: Operating System :: MacOS :: MacOS X
Classifier: Operating System :: Microsoft :: Windows
